{
  "format_version": "1.12",
  "minecraft:recipe_shaped": {
    "description": {
      "identifier": "brewinandchewin:pizza_from_minecraft_brown_mushroom_from_farmersdelight_is_cooked_mutton"
    },
    "key": {
      "f": {
        "tag": "brewinandchewin:cheese_wedges"
      },
      "o": {
        "tag": "farmersdelight:is_cooked_mutton"
      },
      "p": {
        "item": "minecraft:brown_mushroom"
      },
      "t": {
        "item": "farmersdelight:tomato_sauce"
      },
      "w": {
        "item": "minecraft:wheat"
      }
    },
    "pattern": [
      " f ",
      "pto",
      "www"
    ],
    "result": [
      {
        "item": "brewinandchewin:pizza"
      },
      {
        "item": "minecraft:bowl"
      }
    ],
    "tags": [
      "crafting_table"
    ]
  }
}